{
   "coord":{
      "lon":77.2167,
      "lat":28.6667
   },
   "weather":[
      {
         "id":711,
         "main":"Smoke",
         "description":"smoke",
         "icon":"50d"
      }
   ],
   "base":"stations",
   "main":{
      "temp":15.05,
      "feels_like":14.13,
      "temp_min":15.05,
      "temp_max":15.05,
      "pressure":1018,
      "humidity":58
   },
   "visibility":1500,
   "wind":{
      "speed":3.09,
      "deg":270
   },
   "clouds":{
      "all":0
   },
   "dt":1704973162,
   "sys":{
      "type":1,
      "id":9165,
      "country":"IN",
      "sunrise":1704937509,
      "sunset":1704975109
   },
   "timezone":19800,
   "id":1273294,
   "name":"Delhi",
   "cod":200
}
